caplib3.py
caplib3-0.6.12.dist-info/LICENSE
caplib3-0.6.12.dist-info/METADATA
caplib3-0.6.12.dist-info/WHEEL
caplib3-0.6.12.dist-info/top_level.txt
caplib3-0.6.12.dist-info/RECORD
