Metadata-Version: 2.1
Name: caplib3
Version: 0.6.12
Summary: NGS data analysis of capsid libraries
Home-page: https://github.com/damienmarsic/caplib3
Author: Damien Marsic
Author-email: damien.marsic@aliyun.com
Classifier: Programming Language :: Python :: 3
Classifier: License :: OSI Approved :: GNU General Public License v3 (GPLv3)
Classifier: Operating System :: OS Independent
Classifier: Intended Audience :: Science/Research
Classifier: Topic :: Scientific/Engineering :: Bio-Informatics
Requires-Python: >=3.6
License-File: LICENSE
